garpix_vacancy/MANIFEST.in
garpix_vacancy/__init__.py
garpix_vacancy/apps.py
garpix_vacancy/setup.py
garpix_vacancy/urls.py
garpix_vacancy/__pycache__/__init__.cpython-38.pyc
garpix_vacancy/__pycache__/apps.cpython-38.pyc
garpix_vacancy/__pycache__/urls.cpython-38.pyc
garpix_vacancy/admin/__init__.py
garpix_vacancy/admin/contact.py
garpix_vacancy/admin/vacancy.py
garpix_vacancy/admin/__pycache__/__init__.cpython-38.pyc
garpix_vacancy/admin/__pycache__/contact.cpython-38.pyc
garpix_vacancy/admin/__pycache__/vacancy.cpython-38.pyc
garpix_vacancy/models/__init__.py
garpix_vacancy/models/contact.py
garpix_vacancy/models/vacancy.py
garpix_vacancy/models/__pycache__/__init__.cpython-38.pyc
garpix_vacancy/models/__pycache__/contact.cpython-38.pyc
garpix_vacancy/models/__pycache__/vacancy.cpython-38.pyc
garpix_vacancy/serializers/__init__.py
garpix_vacancy/serializers/vacancy.py
garpix_vacancy/serializers/__pycache__/__init__.cpython-38.pyc
garpix_vacancy/serializers/__pycache__/vacancy.cpython-38.pyc
garpix_vacancy/viewsets/__init__.py
garpix_vacancy/viewsets/vacancy.py
garpix_vacancy/viewsets/__pycache__/__init__.cpython-38.pyc
garpix_vacancy/viewsets/__pycache__/vacancy.cpython-38.pyc
garpix_vacancy-1.0.0.dist-info/METADATA
garpix_vacancy-1.0.0.dist-info/WHEEL
garpix_vacancy-1.0.0.dist-info/top_level.txt
garpix_vacancy-1.0.0.dist-info/RECORD
