Metadata-Version: 2.1
Name: garpix-vacancy
Version: 1.0.0
Summary: UNKNOWN
Home-page: https://github.com/garpixcms/garpix_vacancy
Author: Garpix LTD
Author-email: info@garpix.com
License: MIT
Platform: UNKNOWN
Classifier: Development Status :: 4 - Beta
Classifier: Environment :: Web Environment
Classifier: Intended Audience :: Developers
Classifier: License :: OSI Approved :: MIT License
Classifier: Operating System :: OS Independent
Classifier: Programming Language :: Python
Classifier: Framework :: Django
Classifier: Programming Language :: Python :: 3.8
Requires-Dist: garpixcms (>=1.7.1)
